odoo/addons/edi_storage_oca/README.rst
odoo/addons/edi_storage_oca/__init__.py
odoo/addons/edi_storage_oca/__manifest__.py
odoo/addons/edi_storage_oca/utils.py
odoo/addons/edi_storage_oca/data/cron.xml
odoo/addons/edi_storage_oca/demo/edi_backend_demo.xml
odoo/addons/edi_storage_oca/i18n/edi_storage_oca.pot
odoo/addons/edi_storage_oca/i18n/it.po
odoo/addons/edi_storage_oca/migrations/18.0.1.0.0/post-migration.py
odoo/addons/edi_storage_oca/models/__init__.py
odoo/addons/edi_storage_oca/models/edi_backend.py
odoo/addons/edi_storage_oca/models/edi_exchange_record.py
odoo/addons/edi_storage_oca/models/edi_exchange_type.py
odoo/addons/edi_storage_oca/models/edi_oca_storage_handler.py
odoo/addons/edi_storage_oca/readme/CONTRIBUTORS.md
odoo/addons/edi_storage_oca/readme/CREDITS.md
odoo/addons/edi_storage_oca/readme/DESCRIPTION.md
odoo/addons/edi_storage_oca/readme/ROADMAP.md
odoo/addons/edi_storage_oca/readme/USAGE.md
odoo/addons/edi_storage_oca/security/ir_model_access.xml
odoo/addons/edi_storage_oca/static/description/icon.png
odoo/addons/edi_storage_oca/static/description/index.html
odoo/addons/edi_storage_oca/tests/__init__.py
odoo/addons/edi_storage_oca/tests/common.py
odoo/addons/edi_storage_oca/tests/test_edi_backend_storage.py
odoo/addons/edi_storage_oca/tests/test_exchange_type.py
odoo/addons/edi_storage_oca/views/edi_backend_views.xml
odoo_addon_edi_storage_oca-18.0.1.0.2.dist-info/METADATA
odoo_addon_edi_storage_oca-18.0.1.0.2.dist-info/WHEEL
odoo_addon_edi_storage_oca-18.0.1.0.2.dist-info/top_level.txt
odoo_addon_edi_storage_oca-18.0.1.0.2.dist-info/RECORD
